redsim/__init__.py
redsim/costs.py
redsim/market.py
redsim/params.py
redsim/revenue.py
redsim/sim.py
redsim-1.0.1.dist-info/LICENSE
redsim-1.0.1.dist-info/METADATA
redsim-1.0.1.dist-info/WHEEL
redsim-1.0.1.dist-info/top_level.txt
redsim-1.0.1.dist-info/RECORD
