Metadata-Version: 2.1
Name: redsim
Version: 1.0.1
Summary: Simulation framework for Gas Management in Redstone
Author-email: Maria Silva <misilva73@gmail.com>
Project-URL: Homepage, https://github.com/latticexyz/redstone-gas
Classifier: Programming Language :: Python :: 3
Classifier: License :: OSI Approved :: MIT License
Classifier: Operating System :: OS Independent
Requires-Python: >=3.8
License-File: LICENSE
Requires-Dist: numpy
Requires-Dist: pandas
Requires-Dist: scipy
Requires-Dist: tqdm
